<?xml version="1.0" ?>
<release version="1802">
  <day timestamp="2018-11-07">
    <task>
      to-do list prepare. ad hoc, Fanyan, create hana schema
      <time>
        2.00-3.40
        <minutes>100.0</minutes>
      </time>
    </task>
    <task>
      migrate qray lib
      <time>
        5.00-5.30
        <minutes>30.0</minutes>
      </time>
    </task>
    <task>
      cici GACE create 2 job, couple + decouple, 15mins
      <time>
        5.30-5.50
        <minutes>20.0</minutes>
      </time>
    </task>
    <task>
      harness demo
      <time>
        6.00-8.30
        <minutes>150.0</minutes>
      </time>
    </task>
    <task>
      rem/cs
      <time>
        8.30-10.00
        <minutes>90.0</minutes>
      </time>
    </task>
  </day>
  <day timestamp="2018-11-08">
    <task>
      REM/CS, adhoc nick, coy
      <time>
        2.00-3.40
        <minutes>100.0</minutes>
      </time>
    </task>
    <task>
      REM/CS
      <time>
        5.10-6.30
        <minutes>80.0</minutes>
      </time>
    </task>
    <task>
      adhoc, tarisa, cici
      <time>
        6.30-7.30
        <minutes>60.0</minutes>
      </time>
    </task>
    <task>
      REM/CS, tarisa suport
      <time>
        7.30-9.00
        <minutes>90.0</minutes>
      </time>
    </task>
    <task>
      support email
      <time>
        9.00-10.20
        <minutes>80.0</minutes>
      </time>
    </task>
  </day>
  <day timestamp="2018-11-09">
    <task>
      Qray migration follow
      <time>
        2.00-2.30
        <minutes>30.0</minutes>
      </time>
    </task>
    <task>
      Customer issue retro
      <time>
        2.30-3.20
        <minutes>50.0</minutes>
      </time>
    </task>
    <task>
      interview prepar
      <time>
        5.00-7.00
        <minutes>120.0</minutes>
      </time>
    </task>
    <task>
      ad hoc, cici gace
      <time>
        7.00-7.40
        <minutes>40.0</minutes>
      </time>
    </task>
    <task>
      hana enhance check
      <time>
        7.40-8.00
        <minutes>20.0</minutes>
      </time>
    </task>
    <task>
      meeting
      <time>
        8.00-10.00
        <minutes>120.0</minutes>
      </time>
    </task>
    <task>
      hana db column change
      <time>
        2.00-2.30
        <minutes>30.0</minutes>
      </time>
    </task>
    <task>
      sync meeting
      <time>
        2.30-3.40
        <minutes>70.0</minutes>
      </time>
    </task>
    <task>
      jam delta export qa env testing + qray enhance
      <time>
        5.00-9.00
        <minutes>240.0</minutes>
      </time>
    </task>
    <task>
      ad hoc, cici password
      <time>
        9.00-9.40
        <minutes>40.0</minutes>
      </time>
    </task>
    <task>
      qray harness migration, blocked, waiting for Terry's permission apply
      <time>
        2.00-2.40
        <minutes>40.0</minutes>
      </time>
    </task>
    <task>
      task sync, jam delta + hana db check list
      <time>
        2.40-3.20
        <minutes>40.0</minutes>
      </time>
    </task>
    <task>
      supt qray fix
      <time>
        5.00-10.00
        <minutes>300.0</minutes>
      </time>
    </task>
    <task>
      qray migration
      <time>
        2.00-2.30
        <minutes>30.0</minutes>
      </time>
    </task>
    <task>
      preday one training
      <time>
        2.30-3.40
        <minutes>70.0</minutes>
      </time>
    </task>
    <task>
      ant task
      <time>
        5.00-6.30
        <minutes>90.0</minutes>
      </time>
    </task>
    <task>
      SUPT report API
      <time>
        6.30-7.40
        <minutes>70.0</minutes>
      </time>
    </task>
    <task>
      PM support
      <time>
        7.40-8.40
        <minutes>60.0</minutes>
      </time>
    </task>
    <task>
      ant task
      <time>
        8.40-10.00
        <minutes>80.0</minutes>
      </time>
    </task>
    <task>
      qray migration
      <time>
        2.00-3.00
        <minutes>60.0</minutes>
      </time>
    </task>
    <task>
      Siemens analysis
      <time>
        3.00-3.40
        <minutes>40.0</minutes>
      </time>
    </task>
    <task>
      qray migration
      <time>
        5.10-7.10
        <minutes>120.0</minutes>
      </time>
    </task>
    <task>
      Siemens, env is slow
      <time>
        7.10-9.20
        <minutes>130.0</minutes>
      </time>
    </task>
    <task>
      CS ticket
      <time>
        9.20-10.20
        <minutes>60.0</minutes>
      </time>
    </task>
    <task>
      CS ticket, ad hoc coy
      <time>
        2.00-3.00
        <minutes>60.0</minutes>
      </time>
    </task>
    <task>
      ad hoc Sarah, jiao yong
      <time>
        3.00-3.40
        <minutes>40.0</minutes>
      </time>
    </task>
    <task>
      Eric, perf API confirm
      <time>
        5.30-6.20
        <minutes>50.0</minutes>
      </time>
    </task>
    <task>
      qray migration
      <time>
        6.20-6.30
        <minutes>10.0</minutes>
      </time>
    </task>
    <task>
      ad hoc Nic
      <time>
        6.30-7.15
        <minutes>45.0</minutes>
      </time>
    </task>
    <task>
      robust qray
      <time>
        7.20-8.10
        <minutes>50.0</minutes>
      </time>
    </task>
    <task>
      ant task
      <time>
        8.10-8.50
        <minutes>40.0</minutes>
      </time>
    </task>
    <task>
      CS
      <time>
        8.40-9.00
        <minutes>20.0</minutes>
      </time>
    </task>
    <task>
      CS issue
      <time>
        2.00-2.30
        <minutes>30.0</minutes>
      </time>
    </task>
    <task>
      meeting
      <time>
        2.30-3.40
        <minutes>70.0</minutes>
      </time>
    </task>
    <task>
      ad hoc cici
      <time>
        5.00-5.20
        <minutes>20.0</minutes>
      </time>
    </task>
    <task>
      siemens sanity, Ip restriction/ provisioning access
      <time>
        5.20-5.40
        <minutes>20.0</minutes>
      </time>
    </task>
    <task>
      qray migration
      <time>
        5.40-7.00
        <minutes>80.0</minutes>
      </time>
    </task>
    <task>
      jam delta migration
      <time>
        7.00-8.00
        <minutes>60.0</minutes>
      </time>
    </task>
    <task>
      qray migration
      <time>
        8.00-10.00
        <minutes>120.0</minutes>
      </time>
    </task>
    <task>
      fix account
      <time>
        2.00-2.40
        <minutes>40.0</minutes>
      </time>
    </task>
    <task>
      CS issue
      <time>
        2.40-2.50
        <minutes>10.0</minutes>
      </time>
    </task>
    <task>
      ant task finish
      <time>
        2.50-3.40
        <minutes>50.0</minutes>
      </time>
    </task>
    <task>
      ant task finish
      <time>
        5.10-10.00
        <minutes>290.0</minutes>
      </time>
    </task>
    <task>
      UP regular meeting
      <time>
        2.15-3.30
        <minutes>75.0</minutes>
      </time>
    </task>
    <task>
      jam delta process
      <time>
        5.00-7.00
        <minutes>120.0</minutes>
      </time>
    </task>
    <task>
      all hands
      <time>
        7.00-8.50
        <minutes>110.0</minutes>
      </time>
    </task>
    <task>
      jam delta process
      <time>
        8.50-10.00
        <minutes>70.0</minutes>
      </time>
    </task>
    <task>
      CS issue
      <time>
        2.20-3.20
        <minutes>60.0</minutes>
      </time>
    </task>
    <task>
      performance api integration
      <time>
        5.30-7.30
        <minutes>120.0</minutes>
      </time>
    </task>
    <task>
      ad hoc, wang he, provisioning setting
      <time>
        7.40-8.20
        <minutes>40.0</minutes>
      </time>
    </task>
    <task>
      scrum meeting
      <time>
        8.30-9.00
        <minutes>30.0</minutes>
      </time>
    </task>
    <task>
      company creation failed trace, need fix account maybe
      <time>
        9.10-9.50
        <minutes>40.0</minutes>
      </time>
    </task>
    <task>
      ratro
      <time>
        2.30-3.30
        <minutes>60.0</minutes>
      </time>
    </task>
    <task>
      jam delta process, confirm process and file ticket to get testing FTP address, COSD-21048
      <time>
        5.30-5.50
        <minutes>20.0</minutes>
      </time>
    </task>
    <task>
      audit, code remove
      <time>
        5.50-7.50
        <minutes>120.0</minutes>
      </time>
    </task>
    <task>
      preview hana migration ticket
      <time>
        7.50-9.00
        <minutes>70.0</minutes>
      </time>
    </task>
    <task>
      audit report code remove
      <time>
        9.00-10.00
        <minutes>60.0</minutes>
      </time>
    </task>
    <task>
      project meeting
      <time>
        2.30-3.30
        <minutes>60.0</minutes>
      </time>
    </task>
    <task>
      CS issue
      <time>
        5.20-6.20
        <minutes>60.0</minutes>
      </time>
    </task>
    <task>
      KT of instance life cycle, confluence
      <time>
        6.20-11.20
        <minutes>300.0</minutes>
      </time>
    </task>
    <task>
      CDissue/REM
      <time>
        2.00-3.00
        <minutes>60.0</minutes>
      </time>
    </task>
    <task>
      Slack/Jenkins config
      <time>
        3.00-4.00
        <minutes>60.0</minutes>
      </time>
    </task>
    <task>
      Slack/Jenkins config
      <time>
        5.00-7.00
        <minutes>120.0</minutes>
      </time>
    </task>
    <task>
      prepare for KT
      <time>
        7.00-8.30
        <minutes>90.0</minutes>
      </time>
    </task>
    <task>
      Instance Life cycle KT
      <time>
        8.30-9.40
        <minutes>70.0</minutes>
      </time>
    </task>
    <task>
      KT aftermath
      <time>
        9.40-10.10
        <minutes>30.0</minutes>
      </time>
    </task>
    <task>
      CS issue, ip restriction/ftp
      <time>
        2.00-3.40
        <minutes>100.0</minutes>
      </time>
    </task>
    <task>
      fix BQ
      <time>
        5.00-5.30
        <minutes>30.0</minutes>
      </time>
    </task>
    <task>
      testlink auto rate, calculate automation rate of provisioning KT, by the end of Thusday
      <time>
        5.30-7.30
        <minutes>120.0</minutes>
      </time>
    </task>
    <task>
      non-gdpr audit
      <time>
        7.30-10.00
        <minutes>150.0</minutes>
      </time>
    </task>
    <task>
      BQ fix
      <time>
        2.00-4.00
        <minutes>120.0</minutes>
      </time>
    </task>
    <task>
      new job and set capillary turn off, schedule, by the end of tomorrow
      <time>
        5.00-6.00
        <minutes>60.0</minutes>
      </time>
    </task>
    <task>
      non-gdpr test design
      <time>
        6.00-8.30
        <minutes>150.0</minutes>
      </time>
    </task>
    <task>
      scrum meeting
      <time>
        8.30-8.45
        <minutes>15.0</minutes>
      </time>
    </task>
    <task>
      delta job check and COSR ticket
      <time>
        8.45-10.00
        <minutes>75.0</minutes>
      </time>
    </task>
    <task>
      CS ticket
      <time>
        2.00-3.30
        <minutes>90.0</minutes>
      </time>
    </task>
    <task>
      KT, testlink enhance for tools team
      <time>
        4.30-5.20
        <minutes>50.0</minutes>
      </time>
    </task>
    <task>
      non-gdpr test design
      <time>
        5.20-9.30
        <minutes>250.0</minutes>
      </time>
    </task>
    <task>
      ad hoc from nick
      <time>
        9.30-10.00
        <minutes>30.0</minutes>
      </time>
    </task>
  </day>
  <day timestamp="2018-12-01">
    <task>
      Project.meeting
      <time>
        2.30-3.30
        <minutes>60.0</minutes>
      </time>
    </task>
    <task>
      Jam delta verification, sftp account https//sftp4.successfactors.com/EFTClient/Account/Login.htm /I306454_121792 / qHe6Vcn4zz1
      <time>
        5.00-6.30
        <minutes>90.0</minutes>
      </time>
    </task>
    <task>
      India BBM ad hoc
      <time>
        6.30-7.00
        <minutes>30.0</minutes>
      </time>
    </task>
    <task>
      code remove. audit user sync, zouliang, fix check
      <time>
        7.00-7.30
        <minutes>30.0</minutes>
      </time>
    </task>
    <task>
      jenkins &amp; slack migration ++
      <time>
        7.30-10.00
        <minutes>150.0</minutes>
      </time>
    </task>
  </day>
  <day timestamp="2018-12-04">
    <task>
      cs issue, cosd trace, code remove
      <time>
        2.00-3.40
        <minutes>100.0</minutes>
      </time>
    </task>
    <task>
      code remove feature check
      <time>
        5.20-6.30
        <minutes>70.0</minutes>
      </time>
    </task>
    <task>
      instance lifycycle transfer
      <time>
        6.30-8.30
        <minutes>120.0</minutes>
      </time>
    </task>
    <task>
      scrum meeting
      <time>
        8.30-8.50
        <minutes>20.0</minutes>
      </time>
    </task>
    <task>
      ad hoc, cc, jessie, India
      <time>
        8.50-10.10
        <minutes>80.0</minutes>
      </time>
    </task>
  </day>
  <day timestamp="2018-12-05">
    <task>
      cs ticket review
      <time>
        2.00-2.30
        <minutes>30.0</minutes>
      </time>
    </task>
    <task>
      weekly meeting
      <time>
        2.30-3.40
        <minutes>70.0</minutes>
      </time>
    </task>
    <task>
      change user to Kafk process
      <time>
        5.30-8.00
        <minutes>150.0</minutes>
      </time>
    </task>
    <task>
      go through no sql process
      <time>
        8.00-9.00
        <minutes>60.0</minutes>
      </time>
    </task>
    <task>
      document of multiple audit report
      <time>
        9.00-10.00
        <minutes>60.0</minutes>
      </time>
    </task>
  </day>
  <day timestamp="2018-12-06">
    <task>
      document for change user multiple audit record
      <time>
        2.00-3.40
        <minutes>100.0</minutes>
      </time>
    </task>
    <task>
      ad hoc from api, default local
      <time>
        5.00-5.30
        <minutes>30.0</minutes>
      </time>
    </task>
    <task>
      cici ad hoc debug
      <time>
        5.30-6.00
        <minutes>30.0</minutes>
      </time>
    </task>
    <task>
      case of instance lifecycle, confirm with Terry
      <time>
        6.00-6.30
        <minutes>30.0</minutes>
      </time>
    </task>
    <task>
      document for change user multiple audit record
      <time>
        6.30-8.00
        <minutes>90.0</minutes>
      </time>
    </task>
    <task>
      Sarah CAL process check
      <time>
        8.00-10.00
        <minutes>120.0</minutes>
      </time>
    </task>
    <task>
      video about code remove behavior change, PLT-64847
      <time>
        10.30-11.20
        <minutes>50.0</minutes>
      </time>
    </task>
  </day>
  <day timestamp="2018-12-07">
    <task>
      ad hoc, Trista
      <time>
        5.00-6.30
        <minutes>90.0</minutes>
      </time>
    </task>
    <task>
      remove report from provisioning
      <time>
        6.30-6.50
        <minutes>20.0</minutes>
      </time>
    </task>
    <task>
      non-gdpr testing
      <time>
        6.50-8.30
        <minutes>100.0</minutes>
      </time>
    </task>
    <task>
      non-gdpr testlink
      <time>
        8.30-10.00
        <minutes>90.0</minutes>
      </time>
    </task>
  </day>
  <day timestamp="2018-12-08">
    <task>
      Ad hoc, provisioning account
      <time>
        2.00-2.30
        <minutes>30.0</minutes>
      </time>
    </task>
    <task>
      Project meeting
      <time>
        2.30-3.50
        <minutes>80.0</minutes>
      </time>
    </task>
    <task>
      automation
      <time>
        5.00-10.00
        <minutes>300.0</minutes>
      </time>
    </task>
    <task>
      xiaofeng job
      <time>
        2.00-2.30
        <minutes>30.0</minutes>
      </time>
    </task>
    <task>
      all hands
      <time>
        2.30-4.00
        <minutes>90.0</minutes>
      </time>
    </task>
    <task>
      ad hoc, xiaofeng
      <time>
        5.20-5.50
        <minutes>30.0</minutes>
      </time>
    </task>
    <task>
      sap talk
      <time>
        6.00-7.00
        <minutes>60.0</minutes>
      </time>
    </task>
    <task>
      auto, audit - Kafka
      <time>
        7.00-8.30
        <minutes>90.0</minutes>
      </time>
    </task>
    <task>
      scrum
      <time>
        8.30-9.00
        <minutes>30.0</minutes>
      </time>
    </task>
    <task>
      auto, audit - Kafka
      <time>
        9.00-10.00
        <minutes>60.0</minutes>
      </time>
    </task>
    <task>
      CS ticket, jam delta job investigate
      <time>
        2.00-2.30
        <minutes>30.0</minutes>
      </time>
    </task>
    <task>
      auto audit-kafka
      <time>
        2.30-3.40
        <minutes>70.0</minutes>
      </time>
    </task>
    <task>
      auto audit-kafka
      <time>
        5.00-10.00
        <minutes>300.0</minutes>
      </time>
    </task>
    <task>
      fix qray
      <time>
        2.00-3.40
        <minutes>100.0</minutes>
      </time>
    </task>
    <task>
      audit kafka automation
      <time>
        5.00-8.00
        <minutes>180.0</minutes>
      </time>
    </task>
    <task>
      meeting with jessica
      <time>
        8.00-9.00
        <minutes>60.0</minutes>
      </time>
    </task>
    <task>
      audit kafka auto
      <time>
        9.00-10.00
        <minutes>60.0</minutes>
      </time>
    </task>
    <task>
      ad hoc, cici
      <time>
        2.00-3.10
        <minutes>70.0</minutes>
      </time>
    </task>
    <task>
      qray
      <time>
        3.10-3.30
        <minutes>20.0</minutes>
      </time>
    </task>
    <task>
      qray
      <time>
        5.00-6.10
        <minutes>70.0</minutes>
      </time>
    </task>
    <task>
      job - kafka
      <time>
        6.10-10.00
        <minutes>230.0</minutes>
      </time>
    </task>
    <task>
      qray fix
      <time>
        2.00-2.30
        <minutes>30.0</minutes>
      </time>
    </task>
    <task>
      project meeting
      <time>
        2.30-3.30
        <minutes>60.0</minutes>
      </time>
    </task>
    <task>
      provisioing dbpool meeting
      <time>
        3.30-4.20
        <minutes>50.0</minutes>
      </time>
    </task>
    <task>
      ad hoc, yan
      <time>
        5.30-6.00
        <minutes>30.0</minutes>
      </time>
    </task>
    <task>
      provisioning nancy, audit testing
      <time>
        6.00-7.00
        <minutes>60.0</minutes>
      </time>
    </task>
    <task>
      audit auto
      <time>
        7.00-10.00
        <minutes>180.0</minutes>
      </time>
    </task>
    <task>
      ad hoc questions, review email
      <time>
        2.00-2.30
        <minutes>30.0</minutes>
      </time>
    </task>
    <task>
      audit auto
      <time>
        2.30-3.40
        <minutes>70.0</minutes>
      </time>
    </task>
    <task>
      audit auto
      <time>
        5.00-8.00
        <minutes>180.0</minutes>
      </time>
    </task>
    <task>
      scrum meeting 
      <time>
        8.00-8.30
        <minutes>30.0</minutes>
      </time>
    </task>
    <task>
      audit auto
      <time>
        8.30-10.00
        <minutes>90.0</minutes>
      </time>
    </task>
    <task>
      email review, ad hoc
      <time>
        2.10-2.30
        <minutes>20.0</minutes>
      </time>
    </task>
    <task>
      Weekly meeting
      <time>
        2.30-3.30
        <minutes>60.0</minutes>
      </time>
    </task>
    <task>
      Instance life cycle transfer
      <time>
        5.30-7.30
        <minutes>120.0</minutes>
      </time>
    </task>
    <task>
      new feature
      <time>
        7.30-8.30
        <minutes>60.0</minutes>
      </time>
    </task>
    <task>
      instance life cycle transfer
      <time>
        8.30-10.00
        <minutes>90.0</minutes>
      </time>
    </task>
    <task>
      new hire process for lisa
      <time>
        2.00-3.00
        <minutes>60.0</minutes>
      </time>
    </task>
    <task>
      provisioning api enhance
      <time>
        3.00-3.40
        <minutes>40.0</minutes>
      </time>
    </task>
    <task>
      provisioning api enhance investigate
      <time>
        5.00-6.40
        <minutes>100.0</minutes>
      </time>
    </task>
    <task>
      multiple record when change user fix + scrum
      <time>
        6.40-9.30
        <minutes>170.0</minutes>
      </time>
    </task>
    <task>
      audit-kafka
      <time>
        9.30-10.00
        <minutes>30.0</minutes>
      </time>
    </task>
    <task>
      Audit feature fix
      <time>
        2.00-2.40
        <minutes>40.0</minutes>
      </time>
    </task>
    <task>
      Rachel meeting
      <time>
        2.40-3.40
        <minutes>60.0</minutes>
      </time>
    </task>
    <task>
      lisa training
      <time>
        5.30-6.00
        <minutes>30.0</minutes>
      </time>
    </task>
    <task>
      provisioning api enhance
      <time>
        6.00-8.20
        <minutes>140.0</minutes>
      </time>
    </task>
    <task>
      provisioning api auto
      <time>
        8.30-10.00
        <minutes>90.0</minutes>
      </time>
    </task>
    <task>
      Email, ad hoc
      <time>
        2.00-2.30
        <minutes>30.0</minutes>
      </time>
    </task>
    <task>
      Project meeting
      <time>
        2.30-3.30
        <minutes>60.0</minutes>
      </time>
    </task>
    <task>
      ad hoc, olivia fix
      <time>
        5.00-6.10
        <minutes>70.0</minutes>
      </time>
    </task>
    <task>
      Provisioning API
      <time>
        6.10-9.00
        <minutes>170.0</minutes>
      </time>
    </task>
    <task>
      Lisa
      <time>
        9.00-9.25
        <minutes>25.0</minutes>
      </time>
    </task>
  </day>
  <day timestamp="2018-01-02">
    <task>
      Email check
      <time>
        2.15-2.30
        <minutes>15.0</minutes>
      </time>
    </task>
    <task>
      QA meeting
      <time>
        2.30-3.40
        <minutes>70.0</minutes>
      </time>
    </task>
    <task>
      prov api auto
      <time>
        5.30-9.00
        <minutes>210.0</minutes>
      </time>
    </task>
    <task>
      audit-kafka
      <time>
        9.00-10.00
        <minutes>60.0</minutes>
      </time>
    </task>
  </day>
  <day timestamp="2018-01-03">
    <task>
      email + xpi
      <time>
        2.00-3.30
        <minutes>90.0</minutes>
      </time>
    </task>
    <task>
      audit - kafka
      <time>
        5.10-7.30
        <minutes>140.0</minutes>
      </time>
    </task>
    <task>
      xpi document
      <time>
        8.00-8.30
        <minutes>30.0</minutes>
      </time>
    </task>
    <task>
      scrum meeting
      <time>
        8.30-9.00
        <minutes>30.0</minutes>
      </time>
    </task>
    <task>
      audit-kafka job
      <time>
        9.00-10.00
        <minutes>60.0</minutes>
      </time>
    </task>
  </day>
  <day timestamp="2018-01-04">
    <task>
      Create / clone company issue
      <time>
        2.30-3.10
        <minutes>40.0</minutes>
      </time>
    </task>
    <task>
      Create / clone company issue
      <time>
        5.20-7.20
        <minutes>120.0</minutes>
      </time>
    </task>
    <task>
      audit - kafka UI, bad env quite
      <time>
        7.30-8.20
        <minutes>50.0</minutes>
      </time>
    </task>
    <task>
      audit - kafka qray, env like a shit, so does my emotion
      <time>
        8.30-10.00
        <minutes>90.0</minutes>
      </time>
    </task>
  </day>
  <day timestamp="2018-01-05">
    <task>
      Project meeting
      <time>
        2.30-3.40
        <minutes>70.0</minutes>
      </time>
    </task>
    <task>
      audit-kafka
      <time>
        5.30-8.00
        <minutes>150.0</minutes>
      </time>
    </task>
    <task>
      code review
      <time>
        8.00-10.00
        <minutes>120.0</minutes>
      </time>
    </task>
  </day>
  <day timestamp="2018-01-08">
    <task>
      email check
      <time>
        2.15-2.30
        <minutes>15.0</minutes>
      </time>
    </task>
    <task>
      audit - kafka
      <time>
        2.30-3.40
        <minutes>70.0</minutes>
      </time>
    </task>
    <task>
      Lisa code review
      <time>
        4.50-5.20
        <minutes>30.0</minutes>
      </time>
    </task>
    <task>
      audit - kafka
      <time>
        5.20-10.00
        <minutes>280.0</minutes>
      </time>
    </task>
  </day>
  <day timestamp="2018-01-09">
    <task>
      email check + fix code
      <time>
        2.15-3.30
        <minutes>75.0</minutes>
      </time>
    </task>
    <task>
      Audit-kafka
      <time>
        5.00-7.00
        <minutes>120.0</minutes>
      </time>
    </task>
    <task>
      Provisioning Maintenance Meeting
      <time>
        7.00-8.10
        <minutes>70.0</minutes>
      </time>
    </task>
    <task>
      audit-kafka
      <time>
        8.10-11.30
        <minutes>200.0</minutes>
      </time>
    </task>
  </day>
  <day timestamp="2018-01-10">
    <task>
      email + lisa training
      <time>
        2.15-2.40
        <minutes>25.0</minutes>
      </time>
    </task>
    <task>
      audit-kafka
      <time>
        2.40-3.40
        <minutes>60.0</minutes>
      </time>
    </task>
    <task>
      audti - kafka
      <time>
        5.00-7.30
        <minutes>150.0</minutes>
      </time>
    </task>
    <task>
      continues run job setting
      <time>
        7.30-8.30
        <minutes>60.0</minutes>
      </time>
    </task>
    <task>
      audit-kafka
      <time>
        8.30-11.00
        <minutes>150.0</minutes>
      </time>
    </task>
  </day>
  <day timestamp="2018-01-11">
    <task>
      lisa training
      <time>
        2.10-2.30
        <minutes>20.0</minutes>
      </time>
    </task>
    <task>
      audit-kafka ui
      <time>
        2.30-3.40
        <minutes>70.0</minutes>
      </time>
    </task>
    <task>
      team lunch
      <time>
        3.40-6.00
        <minutes>140.0</minutes>
      </time>
    </task>
    <task>
      lisa env config
      <time>
        6.00-7.00
        <minutes>60.0</minutes>
      </time>
    </task>
    <task>
      audit-kafka
      <time>
        7.10-9.00
        <minutes>110.0</minutes>
      </time>
    </task>
    <task>
      D-kom
      <time>
        9.00-10.00
        <minutes>60.0</minutes>
      </time>
    </task>
  </day>
  <day timestamp="2018-01-12">
    <task>
      Email + clone company log fetch
      <time>
        2.15-2.30
        <minutes>15.0</minutes>
      </time>
    </task>
    <task>
      Project meeting
      <time>
        2.30-4.00
        <minutes>90.0</minutes>
      </time>
    </task>
    <task>
      cs issue
      <time>
        5.00-6.00
        <minutes>60.0</minutes>
      </time>
    </task>
    <task>
      translation auto
      <time>
        6.00-6.30
        <minutes>30.0</minutes>
      </time>
    </task>
    <task>
      resolve jira ticket, xpi, cs, rem
      <time>
        6.30-7.40
        <minutes>70.0</minutes>
      </time>
    </task>
    <task>
      jira ticket + qray config + aep config
      <time>
        7.40-8.30
        <minutes>50.0</minutes>
      </time>
    </task>
    <task>
      full analysis
      <time>
        8.30-10.00
        <minutes>90.0</minutes>
      </time>
    </task>
  </day>
  <day timestamp="2018-01-15">
    <task>
      email check + Lisa review code fix
      <time>
        2.15-2.30
        <minutes>15.0</minutes>
      </time>
    </task>
    <task>
      Jira ticket for client version not sync
      <time>
        2.30-3.00
        <minutes>30.0</minutes>
      </time>
    </task>
    <task>
      company instance calculate
      <time>
        3.00-4.00
        <minutes>60.0</minutes>
      </time>
    </task>
    <task>
      translation, static sfmessage sync to read_audit_translations table
      <time>
        5.00-10.30
        <minutes>330.0</minutes>
      </time>
    </task>
    <task>
      company instance management
      <time>
        11.00-11.30
        <minutes>30.0</minutes>
      </time>
    </task>
  </day>
  <day timestamp="2018-01-16">
    <task>
      translation automation
      <time>
        2.15-2.30
        <minutes>15.0</minutes>
      </time>
    </task>
    <task>
      up regular meeting
      <time>
        2.30-3.30
        <minutes>60.0</minutes>
      </time>
    </task>
    <task>
      translation automation
      <time>
        4.50-10.30
        <minutes>340.0</minutes>
      </time>
    </task>
  </day>
  <day timestamp="2018-01-17">
    <task>
      CS ticket, ad hoc Lina 
      <time>
        2.10-3.50
        <minutes>100.0</minutes>
      </time>
    </task>
    <task>
      traslation
      <time>
        7.00-10.00
        <minutes>180.0</minutes>
      </time>
    </task>
    <task>
      Rachel meeting
      <time>
        2.30-3.30
        <minutes>60.0</minutes>
      </time>
    </task>
    <task>
      translation automation
      <time>
        5.20-10.30
        <minutes>310.0</minutes>
      </time>
    </task>
  </day>
  <day timestamp="2018-01-19">
    <task>
      translation job
      <time>
        2.10-2.30
        <minutes>20.0</minutes>
      </time>
    </task>
    <task>
      Project meeting
      <time>
        2.30-3.50
        <minutes>80.0</minutes>
      </time>
    </task>
    <task>
      fix CommonVariable, qray
      <time>
        5.00-6.00
        <minutes>60.0</minutes>
      </time>
    </task>
    <task>
      script to fetch new case
      <time>
        6.00-8.00
        <minutes>120.0</minutes>
      </time>
    </task>
    <task>
      code review
      <time>
        8.00-10.00
        <minutes>120.0</minutes>
      </time>
    </task>
  </day>
  <day timestamp="2018-01-22">
    <task>
      email check
      <time>
        2.20-2.30
        <minutes>10.0</minutes>
      </time>
    </task>
    <task>
      QA all hands
      <time>
        2.30-4.00
        <minutes>90.0</minutes>
      </time>
    </task>
    <task>
      catch up sm_user_info check
      <time>
        5.00-7.00
        <minutes>120.0</minutes>
      </time>
    </task>
    <task>
      Master Data Purge
      <time>
        7.00-10.00
        <minutes>180.0</minutes>
      </time>
    </task>
  </day>
  <day timestamp="2018-01-23">
    <task>
      email check + qray fix
      <time>
        2.15-3.30
        <minutes>75.0</minutes>
      </time>
    </task>
    <task>
      master data purge
      <time>
        5.00-7.00
        <minutes>120.0</minutes>
      </time>
    </task>
    <task>
      JR test design review
      <time>
        7.00-7.40
        <minutes>40.0</minutes>
      </time>
    </task>
    <task>
      master data purge
      <time>
        7.40-10.30
        <minutes>170.0</minutes>
      </time>
    </task>
  </day>
  <day timestamp="2018-01-24">
    <task>
      master data purge
      <time>
        2.15-4.00
        <minutes>105.0</minutes>
      </time>
    </task>
    <task>
      master data purge
      <time>
        5.20-8.00
        <minutes>160.0</minutes>
      </time>
    </task>
    <task>
      birthday party
      <time>
        8.00-8.30
        <minutes>30.0</minutes>
      </time>
    </task>
    <task>
      master data purge
      <time>
        8.30-10.00
        <minutes>90.0</minutes>
      </time>
    </task>
  </day>
  <day timestamp="2018-01-25">
    <task>
      master data purge
      <time>
        2.15-4.00
        <minutes>105.0</minutes>
      </time>
    </task>
    <task>
      master data purge
      <time>
        5.20-10.30
        <minutes>310.0</minutes>
      </time>
    </task>
  </day>
  <day timestamp="2018-01-26">
    <task>
      Project meeting
      <time>
        2.30-4.00
        <minutes>90.0</minutes>
      </time>
    </task>
    <task>
      master data purge
      <time>
        4.50-10.00
        <minutes>310.0</minutes>
      </time>
    </task>
  </day>
  <day timestamp="2018-01-29">
    <task>
      master purge automation
      <time>
        2.15-3.30
        <minutes>75.0</minutes>
      </time>
    </task>
    <task>
      master purge automation
      <time>
        5.00-7.00
        <minutes>120.0</minutes>
      </time>
    </task>
    <task>
      sys audit purge
      <time>
        7.00-10.00
        <minutes>180.0</minutes>
      </time>
    </task>
  </day>
  <day timestamp="2018-01-30">
    <task>
      qa weekly meeting
      <time>
        2.30-3.30
        <minutes>60.0</minutes>
      </time>
    </task>
    <task>
      audit perge
      <time>
        5.30-10.00
        <minutes>270.0</minutes>
      </time>
    </task>
  </day>
  <day timestamp="2018-01-31">
    <task>
      PTO
      <time>
        2.00-4.00
        <minutes>120.0</minutes>
      </time>
    </task>
    <task>
      sys audit purge
      <time>
        5.30-10.30
        <minutes>300.0</minutes>
      </time>
    </task>
  </day>
  <day timestamp="2018-02-01">
    <task>
      audit purge
      <time>
        2.30-3.40
        <minutes>70.0</minutes>
      </time>
    </task>
    <task>
      audit purge
      <time>
        5.30-7.00
        <minutes>90.0</minutes>
      </time>
    </task>
    <task>
      core team sync up
      <time>
        7.00-8.00
        <minutes>60.0</minutes>
      </time>
    </task>
    <task>
      audit purge
      <time>
        8.00-10.00
        <minutes>120.0</minutes>
      </time>
    </task>
  </day>
  <day timestamp="2018-02-02">
    <task>
      project meeting
      <time>
        2.30-3.40
        <minutes>70.0</minutes>
      </time>
    </task>
    <task>
      audit purge
      <time>
        5.30-10.00
        <minutes>270.0</minutes>
      </time>
    </task>
  </day>
  <day timestamp="2018-02-05">
    <task>
      email check + full run check
      <time>
        2.20-3.40
        <minutes>80.0</minutes>
      </time>
    </task>
    <task>
      full run check
      <time>
        5.00-10.00
        <minutes>300.0</minutes>
      </time>
    </task>
  </day>
  <day timestamp="2018-02-06">
    <task>
      full analysis
      <time>
        2.20-3.40
        <minutes>80.0</minutes>
      </time>
    </task>
    <task>
      full analysis
      <time>
        5.00-10.00
        <minutes>300.0</minutes>
      </time>
    </task>
  </day>
  <day timestamp="2018-02-07">
    <task>
      full analysis
      <time>
        2.20-3.40
        <minutes>80.0</minutes>
      </time>
    </task>
    <task>
      ad hoc, nancy, Lisa
      <time>
        4.40-5.40
        <minutes>60.0</minutes>
      </time>
    </task>
    <task>
      full analysis
      <time>
        5.40-10.00
        <minutes>260.0</minutes>
      </time>
    </task>
  </day>
  <day timestamp="2018-02-08">
    <task>
      full analysis
      <time>
        2.20-3.40
        <minutes>80.0</minutes>
      </time>
    </task>
    <task>
      full analysis
      <time>
        5.20-10.20
        <minutes>300.0</minutes>
      </time>
    </task>
  </day>
  <day timestamp="2018-02-09">
    <task>
      CS ticket
      <time>
        2.00-2.30
        <minutes>30.0</minutes>
      </time>
    </task>
    <task>
      project meeting
      <time>
        2.30-3.40
        <minutes>70.0</minutes>
      </time>
    </task>
    <task>
      demo meeting
      <time>
        5.30-6.20
        <minutes>50.0</minutes>
      </time>
    </task>
    <task>
      cs ticket
      <time>
        6.20-6.40
        <minutes>20.0</minutes>
      </time>
    </task>
    <task>
      jessie, qray instance migrate
      <time>
        6.40-7.30
        <minutes>50.0</minutes>
      </time>
    </task>
    <task>
      CS ticket + investigate
      <time>
        7.30-9.20
        <minutes>110.0</minutes>
      </time>
    </task>
    <task>
      Rebacca, XPI
      <time>
        9.20-10.00
        <minutes>40.0</minutes>
      </time>
    </task>
  </day>
  <day timestamp="2018-02-12">
    <task>
      full run
      <time>
        5.00-10.00
        <minutes>300.0</minutes>
      </time>
    </task>
  </day>
  <day timestamp="2018-02-13">
    <task>
      full run
      <time>
        2.20-4.00
        <minutes>100.0</minutes>
      </time>
    </task>
    <task>
      full run
      <time>
        5.00-11.00
        <minutes>360.0</minutes>
      </time>
    </task>
  </day>
</release>
